Metadata-Version: 2.1
Name: dealfortheday
Version: 0.2.1
Summary: deal of the day generator
Home-page: 
Author: Prakash Shankar Mishra
Author-email: x21172684@student.ncirl.ie
License: MIT
Keywords: dealforthedaygenerator
Classifier: Development Status :: 5 - Production/Stable
Classifier: Intended Audience :: Education
Classifier: Operating System :: Microsoft :: Windows :: Windows 10
Classifier: License :: OSI Approved :: MIT License
Classifier: Programming Language :: Python :: 3
License-File: LICENCE.txt
